README.rst
setup.cfg
setup.py
restinmagento/__init__.py
restinmagento/backend.py
restinmagento/collectionmanager.py
restinmagento/compat.py
restinmagento/model.py
restinmagento/oauth.py
restinmagento/operators.py
restinmagento/queryset.py
restinmagento/resource.py
restinmagento/scripts.py
restinmagento.egg-info/PKG-INFO
restinmagento.egg-info/SOURCES.txt
restinmagento.egg-info/dependency_links.txt
restinmagento.egg-info/entry_points.txt
restinmagento.egg-info/requires.txt
restinmagento.egg-info/top_level.txt
restinmagento.egg-info/zip-safe
restinmagento/tests/__init__.py
restinmagento/tests/test_collectionmanager.py
restinmagento/tests/test_model.py
restinmagento/tests/test_operators.py
restinmagento/tests/test_queryset.py
restinmagento/tests/test_resource.py
restinmagento/tests/test_testutils.py