Metadata-Version: 1.1
Name: restinmagento
Version: 0.4.2
Summary: REST client for the magento platform
Home-page: https://bitbucket.org/jmsi/restinmagento
Author: Emmanuel Cazenave
Author-email: emmanuel.cazenave@jmsinfor.com
License: MIT
Keywords: REST,Magento,client
Platform: UNKNOWN
Classifier: Programming Language :: Python :: 2.7
Classifier: Programming Language :: Python :: 3.3
Classifier: Development Status :: 3 - Alpha
Classifier: Environment :: Other Environment
Classifier: Intended Audience :: Developers
Classifier: License :: OSI Approved :: MIT License
Classifier: Operating System :: OS Independent
Classifier: Topic :: Software Development :: Libraries :: Python Modules
